{
"name": "kibbles-casting-compendium",
"title": "Kibbles' Casting Compendium",
"description": "A complete compendium of Kibbles' Spells",
"author": "KibblesTasty",
"version": "2.1",
"minimumCoreVersion": "0.6.0",
"compatibility": {
    "minimum": "10",
    "verified": "10.291"
  },
"manifest": "https://raw.githubusercontent.com/KibblesTasty/kibbles-casting-compendium/main/module.json",
"download": "https://github.com/KibblesTasty/kibbles-casting-compendium/releases/download/archive/kibbles-casting-compendium-main.zip",
"keywords" : [
			"spells"
		],
"packs": [
			{
			"name": "kibbles-casting-compendium",
			"label": "Kibbles' Casting Compendium",
			"system": "dnd5e",
			"path": "packs/kibbles-casting-compendium.db",
			"entity": "Item",
			"module": "kibbles-casting-compendium"
			}
		],
"authors": [
			{
			  "name": "KibblesTasty",
			  "url": "https://kthomebrew.com"
			}
		]
}
